PartehDB/__init__.py
PartehDB/base.py
PartehDB-1.0.4.dist-info/LICENSE
PartehDB-1.0.4.dist-info/METADATA
PartehDB-1.0.4.dist-info/WHEEL
PartehDB-1.0.4.dist-info/top_level.txt
PartehDB-1.0.4.dist-info/RECORD
