Metadata-Version: 2.1
Name: PartehDB
Version: 1.0.4
Summary: A python library that lets you create a custom database.
Author-email: PartehPackages <parteh0754.coding.guy@gmail.com>
Project-URL: Homepage, https://www.youtube.com/watch?v=a3Z7zEc7AXQ
Project-URL: Bug Tracker, https://www.youtube.com/watch?v=a3Z7zEc7AXQ
Classifier: Programming Language :: Python :: 3
Classifier: License :: OSI Approved :: MIT License
Classifier: Operating System :: OS Independent
Requires-Python: >=3.7
License-File: LICENSE
